[
  {
    "path": "images/small/40/400b4611.jpg"
  },
  {
    "questions": [
      {
        "question": "What is the primary shape of the depicted glass protector?",
        "answer": "Rectangular"
      },
      {
        "question": "What appears to be the dominant color of the outlined glass protector?",
        "answer": "Clear"
      },
      {
        "question": "Considering the image, what material is the product seemingly made of?",
        "answer": "Glass"
      },
      {
        "question": "Based on the visual representation, what is the apparent texture of the glass?",
        "answer": "Smooth"
      },
      {
        "question": "Does the image show any noticeable markings or patterns on the glass?",
        "answer": "None"
      },
      {
        "question": "Judging by the illustration, what is the overall design style of the protector?",
        "answer": "Minimalist"
      },
      {
        "question": "From the provided diagram, what seems to be the function of this item?",
        "answer": "Protection"
      },
      {
        "question": "Does the image show any apparent curves or bends in the glass protector?",
        "answer": "No"
      },
      {
        "question": "What color are the lines used for outlining the glass dimensions?",
        "answer": "Blue"
      },
      {
        "question": "What unit of measurement is used to denote the glass dimensions?",
        "answer": "Millimeters"
      },
      {
        "question": "Based on the image, is the glass protector designed for a specific device?",
        "answer": "Yes"
      },
      {
        "question": "Does the illustration depict any visible branding or logos on the glass?",
        "answer": "No"
      },
      {
        "question": "Judging by the dimensions, is this a large or small screen protector?",
        "answer": "Small"
      },
      {
        "question": "Considering the image, does the protector have a frame or border?",
        "answer": "Yes"
      },
      {
        "question": "What is the overall visual impression of the product's design?",
        "answer": "Simple"
      }
    ]
  }
]