[
  {
    "path": "images/small/89/8981537b.jpg"
  },
  {
    "questions": [
      {
        "question": "What is the predominant color of the packaging box?",
        "answer": "Gray"
      },
      {
        "question": "What is the primary color of the label on the box?",
        "answer": "Green"
      },
      {
        "question": "What is the shape of the product packaging?",
        "answer": "Rectangular"
      },
      {
        "question": "What is the material of the outer packaging, visually?",
        "answer": "Cardboard"
      },
      {
        "question": "What herb is depicted on the product label?",
        "answer": "Marjoram"
      },
      {
        "question": "What is the state of the marjoram inside, as indicated on the label?",
        "answer": "Dried"
      },
      {
        "question": "Describe the form of the marjoram inside, as stated on the label?",
        "answer": "Chopped"
      },
      {
        "question": "What graphic design element is prominently featured on the label?",
        "answer": "Scattered"
      },
      {
        "question": "What brand name is visible on the packaging?",
        "answer": "Happy"
      },
      {
        "question": "What word is shown after 'Happy' on the label?",
        "answer": "Belly"
      },
      {
        "question": "What is the texture of the packaging box, visually?",
        "answer": "Smooth"
      },
      {
        "question": "Describe the overall style of the product's packaging design?",
        "answer": "Minimalist"
      },
      {
        "question": "What is the print style of the text on the label?",
        "answer": "Sans-serif"
      },
      {
        "question": "Is the label design symmetrical or asymmetrical?",
        "answer": "Asymmetrical"
      },
      {
        "question": "What is the overall tone of the product's branding, judging from visuals?",
        "answer": "Earthy"
      }
    ]
  }
]