[
  {
    "path": "images/small/16/16b15e19.jpg"
  },
  {
    "questions": [
      {
        "question": "What is the predominant color of the plush toy rabbit?",
        "answer": "Blue"
      },
      {
        "question": "What material appears to be used in constructing this stuffed rabbit?",
        "answer": "Polyester"
      },
      {
        "question": "What is the overall shape and form of the presented plush toy?",
        "answer": "Rabbit"
      },
      {
        "question": "What color is the ribbon adorning the rabbit's neck?",
        "answer": "Pink"
      },
      {
        "question": "Describe the texture of the plush toy's fur visually.",
        "answer": "Fuzzy"
      },
      {
        "question": "What type of stitching is visually apparent on the seams?",
        "answer": "Sturdy"
      },
      {
        "question": "Are there any noticeable markings or embroidery details on the plush toy?",
        "answer": "None"
      },
      {
        "question": "Considering its features, what is the intended use of this item?",
        "answer": "Toy"
      },
      {
        "question": "Does the rabbit possess any visible accessories aside from the ribbon?",
        "answer": "No"
      },
      {
        "question": "What is the approximate size of the plush toy relative to a human hand?",
        "answer": "Small"
      },
      {
        "question": "Considering the image, does the rabbit appear to be a single-piece design?",
        "answer": "Yes"
      },
      {
        "question": "Does the image show any noticeable damage or flaws in the plush toy?",
        "answer": "No"
      },
      {
        "question": "From the image alone, can you estimate the rabbit's height?",
        "answer": "Small"
      },
      {
        "question": "What is the apparent expression portrayed on the rabbit's face?",
        "answer": "Cute"
      },
      {
        "question": "Does the plush toy seem appropriately soft for cuddling?",
        "answer": "Yes"
      }
    ]
  }
]