[
  {
    "path": "images/small/ed/eddc5143.jpg"
  },
  {
    "questions": [
      {
        "question": "What is the predominant color of the phone case's main design?",
        "answer": "Black"
      },
      {
        "question": "What word is prominently displayed on the phone case?",
        "answer": "Meow"
      },
      {
        "question": "What animal's facial features are depicted in a minimalist style?",
        "answer": "Cat"
      },
      {
        "question": "What shape is the overall phone case design?",
        "answer": "Rectangular"
      },
      {
        "question": "What color are the cat's ears and whiskers in the illustration?",
        "answer": "White"
      },
      {
        "question": "What design element is incorporated into the cat's nose area?",
        "answer": "Heart"
      },
      {
        "question": "What appears to be the material of the phone case's border?",
        "answer": "Plastic"
      },
      {
        "question": "Considering the image, what is the apparent texture of the phone case?",
        "answer": "Smooth"
      },
      {
        "question": "What is the style of the illustration of the cat's face?",
        "answer": "Minimalist"
      },
      {
        "question": "Based on visual cues, what is the likely finish of the phone case?",
        "answer": "Matte"
      },
      {
        "question": "What is the font style used for the word 'Meow' on the case?",
        "answer": "Sans-serif"
      },
      {
        "question": "Describe the overall visual aesthetic of the phone case design.",
        "answer": "Simple"
      },
      {
        "question": "What seems to be the printing technique used on the phone case?",
        "answer": "Digital"
      },
      {
        "question": "Does the phone case show any additional markings or logos besides the cat design?",
        "answer": "No"
      },
      {
        "question": "What is the apparent level of detail in the cat's facial features design?",
        "answer": "Low"
      }
    ]
  }
]