[
  {
    "path": "images/small/cb/cb78ba6e.jpg"
  },
  {
    "questions": [
      {
        "question": "What is the dominant color displayed on the primary surface of the phone case?",
        "answer": "Blue"
      },
      {
        "question": "What letter is prominently featured in a gold-colored, uppercase style at the center of the phone case design?",
        "answer": "J"
      },
      {
        "question": "What appears to be the material used for the construction of this protective phone case?",
        "answer": "Silicone"
      },
      {
        "question": "Describe the style of the decorative border encompassing the central letter on the phone case.",
        "answer": "Floral"
      },
      {
        "question": "What color is the decorative border surrounding the main letter on the phone case?",
        "answer": "Gold"
      },
      {
        "question": "Considering the image, what seems to be the main function of this product?",
        "answer": "Protection"
      },
      {
        "question": "Based on the visual, what design element is featured on the sides of the phone case?",
        "answer": "Transparent"
      },
      {
        "question": "What characteristic of the print on the back of the case is visually suggested?",
        "answer": "Printed"
      },
      {
        "question": "What seems to be the printing technique applied to the back of the phone case, as evidenced by the image?",
        "answer": "Back"
      },
      {
        "question": "Judging by the visual, what is suggested about the accessibility of the phone's ports?",
        "answer": "Accessible"
      },
      {
        "question": "Does the image suggest any protection against scratches on the phone case?",
        "answer": "Yes"
      },
      {
        "question": "Does the image suggest any protection against fingerprints on the phone case?",
        "answer": "Yes"
      },
      {
        "question": "Does the image suggest any protection against dust on the phone case?",
        "answer": "Yes"
      },
      {
        "question": "What is the overall shape of the phone case, as depicted in the image?",
        "answer": "Rectangular"
      },
      {
        "question": "Describe the overall visual style of the phone case design as depicted in the image.",
        "answer": "Ornate"
      }
    ]
  }
]