[
  {
    "path": "images/small/6b/6bfc4c08.jpg"
  },
  {
    "questions": [
      {
        "question": "What is the dominant color of the screen protector's visible edges?",
        "answer": "Green"
      },
      {
        "question": "Considering the image, what seems to be the overall shape of the screen protector?",
        "answer": "Rectangular"
      },
      {
        "question": "Based on the visual appearance, what material is primarily used for this screen protector?",
        "answer": "Glass"
      },
      {
        "question": "Judging by its visual clarity, what is the apparent transparency level of the protector?",
        "answer": "High"
      },
      {
        "question": "Does the screen protector appear to have any noticeable texture or surface treatment?",
        "answer": "Smooth"
      },
      {
        "question": "Are there any visible markings or logos directly on the screen protector itself?",
        "answer": "None"
      },
      {
        "question": "From the visual evidence provided, is there any visible damage or imperfection on the screen protector?",
        "answer": "No"
      },
      {
        "question": "Considering the image, does the protector appear to fully cover the device's screen?",
        "answer": "Yes"
      },
      {
        "question": "What is the apparent visual finish of the screen protector's surface?",
        "answer": "Glossy"
      },
      {
        "question": "Observing the water droplets, what is the apparent interaction with the screen protector's surface?",
        "answer": "Repellent"
      },
      {
        "question": "Judging from the image, what is the relative thickness of the screen protector?",
        "answer": "Thin"
      },
      {
        "question": "Considering the visible edges, does the protector exhibit a consistent edge profile?",
        "answer": "Yes"
      },
      {
        "question": "Does the screen protector's application seem to have caused any bubbles beneath it?",
        "answer": "No"
      },
      {
        "question": "Based on the visual clarity, does it obstruct the device's screen display?",
        "answer": "No"
      },
      {
        "question": "From the image, can you determine if any adhesive is visibly present?",
        "answer": "No"
      }
    ]
  }
]