[
  {
    "path": "images/small/80/80d7597e.jpg"
  },
  {
    "questions": [
      {
        "question": "What is the predominant color of the depicted donut on the phone case?",
        "answer": "Pink"
      },
      {
        "question": "What topping covers the donut image showcased on the phone case?",
        "answer": "Sprinkles"
      },
      {
        "question": "What is the overall shape of the illustrated donut on the phone case?",
        "answer": "Circular"
      },
      {
        "question": "What is the primary color of the background on the phone case?",
        "answer": "Blue"
      },
      {
        "question": "What type of food item is prominently displayed on this phone case?",
        "answer": "Donut"
      },
      {
        "question": "What appears to be the material of the phone case itself?",
        "answer": "Plastic"
      },
      {
        "question": "Considering the image, what is the general style of the phone case design?",
        "answer": "Cute"
      },
      {
        "question": "Describe the finish of the phone case's surface, based on visual appearance.",
        "answer": "Matte"
      },
      {
        "question": "What is the apparent texture of the illustrated donut's icing?",
        "answer": "Smooth"
      },
      {
        "question": "What is the color of the donut's filling as depicted in the image?",
        "answer": "Pink"
      },
      {
        "question": "What shape does the hole in the center of the donut appear to have?",
        "answer": "Circular"
      },
      {
        "question": "Besides the donut, are there any other prominent design elements?",
        "answer": "None"
      },
      {
        "question": "What color are the majority of the sprinkles on the phone case's donut?",
        "answer": "Multicolored"
      },
      {
        "question": "Considering the phone case's design, what is its implied target demographic?",
        "answer": "Youth"
      },
      {
        "question": "Based on the image, what is the phone case's apparent form factor?",
        "answer": "Slim"
      }
    ]
  }
]