[
  {
    "path": "images/small/30/306f0c3b.jpg"
  },
  {
    "questions": [
      {
        "question": "What is the dominant color displayed on the majority of the vase's surface?",
        "answer": "White"
      },
      {
        "question": "Describe the textural appearance of the vase's primary color field.",
        "answer": "Speckled"
      },
      {
        "question": "What color is the broad horizontal band near the base of the vase?",
        "answer": "DarkGray"
      },
      {
        "question": "Identify the color of the uppermost horizontal band encircling the vase's body?",
        "answer": "Yellow"
      },
      {
        "question": "What is the precise color of the middle horizontal stripe on the vase?",
        "answer": "Teal"
      },
      {
        "question": "What is the overall shape of this decorative ceramic vessel?",
        "answer": "Curved"
      },
      {
        "question": "Considering the visual characteristics, what material appears to be used in the construction of this item?",
        "answer": "Ceramic"
      },
      {
        "question": "What is the most noticeable design element of this vase, excluding its color?",
        "answer": "Stripes"
      },
      {
        "question": "Describe the general appearance of the vase's neck or top opening.",
        "answer": "Rounded"
      },
      {
        "question": "Based on visual characteristics alone, what is the intended function of this object?",
        "answer": "Vase"
      },
      {
        "question": "What is the visual texture of the horizontal color bands, smooth or rough?",
        "answer": "Smooth"
      },
      {
        "question": "Ignoring color, what is the geometrical form of the horizontal markings?",
        "answer": "Bands"
      },
      {
        "question": "How many distinct color bands appear near the bottom of the ceramic vase?",
        "answer": "Three"
      },
      {
        "question": "What is the visible finish or surface treatment on the vase's body?",
        "answer": "Matte"
      },
      {
        "question": "Does the vase's design show any noticeable patterns beyond the horizontal stripes?",
        "answer": "No"
      }
    ]
  }
]