[
  {
    "path": "images/small/07/0725c76d.jpg"
  },
  {
    "questions": [
      {
        "question": "What is the dominant color of the visible portion of the shoe?",
        "answer": "Burgundy"
      },
      {
        "question": "What material appears to constitute the main upper of the shoe?",
        "answer": "Suede"
      },
      {
        "question": "What kind of sole does this shoe prominently display?",
        "answer": "Platform"
      },
      {
        "question": "Describe the texture of the visible trim at the top of the shoe.",
        "answer": "Fuzzy"
      },
      {
        "question": "What color is the visible portion of the shoe's sole?",
        "answer": "White"
      },
      {
        "question": "What is the general shape of the shoe's toe box area?",
        "answer": "Rounded"
      },
      {
        "question": "What is the apparent material of the shoe's trim?",
        "answer": "Shearling"
      },
      {
        "question": "Describe the overall style of this footwear item?",
        "answer": "Bootie"
      },
      {
        "question": "What type of footwear is depicted in the image?",
        "answer": "Boots"
      },
      {
        "question": "What design element is present at the top edge of the shoe?",
        "answer": "Fringe"
      },
      {
        "question": "What is the apparent height of the shoe's heel?",
        "answer": "High"
      },
      {
        "question": "What is the visible texture of the primary shoe material?",
        "answer": "Napped"
      },
      {
        "question": "What seems to be the texture of the inner lining?",
        "answer": "Soft"
      },
      {
        "question": "Considering the materials, what is the likely season of use?",
        "answer": "Winter"
      },
      {
        "question": "What is the overall construction of the shoe's base?",
        "answer": "Solid"
      }
    ]
  }
]