[
  {
    "path": "images/small/10/10eeba68.jpg"
  },
  {
    "questions": [
      {
        "question": "What is the primary color of the coffee table's top surface?",
        "answer": "Beige"
      },
      {
        "question": "What material appears to constitute the table's main body?",
        "answer": "Wood"
      },
      {
        "question": "Describe the finish of the wood-like surface of the coffee table.",
        "answer": "Matte"
      },
      {
        "question": "What is the apparent material of the lift-top mechanism?",
        "answer": "Metal"
      },
      {
        "question": "What color is the metal accent used in the lift-top mechanism?",
        "answer": "Black"
      },
      {
        "question": "What is the shape of the table's overall silhouette?",
        "answer": "Rectangular"
      },
      {
        "question": "What material seems to form the smaller, inner surface beneath the lift-top?",
        "answer": "Glass"
      },
      {
        "question": "What color is the glass insert visible underneath the top?",
        "answer": "White"
      },
      {
        "question": "Describe the style of the table's legs, in terms of their shape?",
        "answer": "Linear"
      },
      {
        "question": "What seems to be the finish of the metal legs supporting the coffee table?",
        "answer": "Silver"
      },
      {
        "question": "What is the apparent function of the lift-top mechanism?",
        "answer": "Lifting"
      },
      {
        "question": "Considering the storage, how many compartments does the table appear to have?",
        "answer": "Two"
      },
      {
        "question": "What is the style of the visible storage compartments beneath the top?",
        "answer": "Open"
      },
      {
        "question": "Considering the table's overall design, what style would best describe it?",
        "answer": "Modern"
      },
      {
        "question": "What is the visible mechanism enabling the top to lift and expand?",
        "answer": "Hinges"
      }
    ]
  }
]