[
  {
    "path": "images/small/e6/e602ff06.jpg"
  },
  {
    "questions": [
      {
        "question": "What is the primary color of the laundry hamper's fabric?",
        "answer": "Beige"
      },
      {
        "question": "What word is prominently displayed on the hamper's front?",
        "answer": "Laundry"
      },
      {
        "question": "What material appears to constitute the main body of the hamper?",
        "answer": "Fabric"
      },
      {
        "question": "What is the overall shape of the laundry hamper presented?",
        "answer": "Rectangular"
      },
      {
        "question": "What type of wheels support the bottom of the hamper?",
        "answer": "Caster"
      },
      {
        "question": "Describe the texture of the visible fabric on the hamper.",
        "answer": "Smooth"
      },
      {
        "question": "What is the color of the text on the laundry hamper's face?",
        "answer": "Black"
      },
      {
        "question": "How many wheels are visibly supporting the hamper?",
        "answer": "Four"
      },
      {
        "question": "What kind of handle is integrated into the top of the hamper?",
        "answer": "Cut-out"
      },
      {
        "question": "What is the apparent style of the lettering on the hamper?",
        "answer": "Sans-serif"
      },
      {
        "question": "Considering its shape, what is the hamper's orientation?",
        "answer": "Vertical"
      },
      {
        "question": "What is the apparent size of the text in relation to the hamper?",
        "answer": "Large"
      },
      {
        "question": "Describe the color of the wheels visible on the hamper.",
        "answer": "Black"
      },
      {
        "question": "What seems to be the overall design aesthetic of this hamper?",
        "answer": "Minimalist"
      },
      {
        "question": "What is the apparent function of the small tag visible on the top?",
        "answer": "Label"
      }
    ]
  }
]