[
  {
    "path": "images/small/17/173e9176.jpg"
  },
  {
    "questions": [
      {
        "question": "Considering the overall form, what best describes the container's three-dimensional geometry, as it is visibly presented?",
        "answer": "Curved"
      },
      {
        "question": "What is the predominant hue observed across the majority of the container's surface area?",
        "answer": "White"
      },
      {
        "question": "From a visual standpoint, what appears to be the primary material used in the construction of this product?",
        "answer": "Plastic"
      },
      {
        "question": "Based on the visual details, what kind of cap or closure is affixed to the top of this bottle?",
        "answer": "Flip"
      },
      {
        "question": "Disregarding text, what is the most noticeable graphic design element printed on the container's rear panel?",
        "answer": "Text"
      },
      {
        "question": "Judging by visual inspection alone, what can be said about the surface texture of the bottle?",
        "answer": "Smooth"
      },
      {
        "question": "What is the overall shape of the container as visible in the provided image?",
        "answer": "Round"
      },
      {
        "question": "What is the observed color of the bottle's cap, based on direct visual inspection?",
        "answer": "White"
      },
      {
        "question": "Considering the printed information, what is the most dominant color of the text elements?",
        "answer": "Black"
      },
      {
        "question": "What is the primary method of identification on the bottle's rear side, as visually confirmed?",
        "answer": "Barcode"
      },
      {
        "question": "Given the image, does the bottle exhibit any apparent surface decorations beyond the text?",
        "answer": "No"
      },
      {
        "question": "What specific type of container is depicted in the image, based on its visual characteristics?",
        "answer": "Bottle"
      },
      {
        "question": "What is the visible color of the labeling on the back of the bottle?",
        "answer": "White"
      },
      {
        "question": "What kind of text is visible on the rear of the container?",
        "answer": "Descriptive"
      },
      {
        "question": "Ignoring the textual details, what is the general nature of the rear panel's visual presentation?",
        "answer": "Plain"
      }
    ]
  }
]