[
  {
    "path": "images/small/38/3800faf4.jpg"
  },
  {
    "questions": [
      {
        "question": "What is the dominant color scheme of the depicted design on the phone case?",
        "answer": "Blue"
      },
      {
        "question": "What celestial body is prominently featured in the phone case's artwork?",
        "answer": "Moon"
      },
      {
        "question": "What type of tree is stylized in the central motif of the phone case design?",
        "answer": "Heart"
      },
      {
        "question": "Describe the apparent texture of the phone case's outer shell, based on visual observation?",
        "answer": "Smooth"
      },
      {
        "question": "What color are the light sources or blossoms depicted on and around the tree?",
        "answer": "Gold"
      },
      {
        "question": "What is the overall shape of the phone case as depicted in the provided image?",
        "answer": "Rectangular"
      },
      {
        "question": "What material appears to constitute the primary body of the phone case?",
        "answer": "Plastic"
      },
      {
        "question": "What is the color of the background against which the tree and moon are depicted?",
        "answer": "Dark"
      },
      {
        "question": "Considering the image, what is the general style of the artwork on the phone case?",
        "answer": "Artistic"
      },
      {
        "question": "Based on visual analysis, what seems to be the primary design element?",
        "answer": "Tree"
      },
      {
        "question": "Judging from the image, what appears to be the level of detail in the tree's design?",
        "answer": "High"
      },
      {
        "question": "Does the image show any apparent text or branding on the case itself?",
        "answer": "No"
      },
      {
        "question": "What is the general visual impression of the artwork \u2013 whimsical or realistic?",
        "answer": "Whimsical"
      },
      {
        "question": "What color is the visible portion of the phone's camera housing, as seen through the case?",
        "answer": "Blue"
      },
      {
        "question": "Describe the apparent ground depicted beneath the tree in the phone case art.",
        "answer": "Green"
      }
    ]
  }
]