[
  {
    "path": "images/small/f3/f38ef076.jpg"
  },
  {
    "questions": [
      {
        "question": "What is the overall color or finish of the door hinge?",
        "answer": "Antique"
      },
      {
        "question": "What appears to be the primary material of the hinge?",
        "answer": "Metal"
      },
      {
        "question": "What is the predominant shape of each hinge leaf?",
        "answer": "Rectangular"
      },
      {
        "question": "Considering the hinge's design, what type of door would this likely fit?",
        "answer": "Standard"
      },
      {
        "question": "How many screw holes are visible on each hinge leaf?",
        "answer": "Four"
      },
      {
        "question": "What is the apparent texture of the hinge's surface?",
        "answer": "Smooth"
      },
      {
        "question": "Based on the image, what is the finish of the included screws?",
        "answer": "Dark"
      },
      {
        "question": "What is the visible shape of the included mounting screws?",
        "answer": "Phillips"
      },
      {
        "question": "What seems to be the approximate number of screws provided?",
        "answer": "Eight"
      },
      {
        "question": "Does the hinge design include any visible decorative elements?",
        "answer": "None"
      },
      {
        "question": "What is the apparent style of the hinge's barrel design?",
        "answer": "Cylindrical"
      },
      {
        "question": "Considering the overall design, what type of joint does the hinge utilize?",
        "answer": "Pin"
      },
      {
        "question": "Judging by the image, is the hinge design for right-handed or left-handed doors?",
        "answer": "Neither"
      },
      {
        "question": "What is the apparent size of the hinge relative to a typical door?",
        "answer": "Standard"
      },
      {
        "question": "What appears to be the primary function of this product?",
        "answer": "Joining"
      }
    ]
  }
]