[
  {
    "path": "images/small/4b/4bd57e37.jpg"
  },
  {
    "questions": [
      {
        "question": "What is the overall shape of each individual light fixture?",
        "answer": "Sphere"
      },
      {
        "question": "What primary metal finish is prominently displayed on the fixture?",
        "answer": "Brass"
      },
      {
        "question": "Describe the texture of the outer globe material, appearing somewhat opaque?",
        "answer": "Frosted"
      },
      {
        "question": "How many individual light globes are integrated into the single fixture?",
        "answer": "Three"
      },
      {
        "question": "What is the dominant color of the light fixture's metal components?",
        "answer": "Gold"
      },
      {
        "question": "What is the apparent material of the light diffusing globes?",
        "answer": "Glass"
      },
      {
        "question": "What is the shape of the backplate supporting the light globes?",
        "answer": "Rectangular"
      },
      {
        "question": "Considering the metal, what is the overall style or finish of the fixture?",
        "answer": "Matte"
      },
      {
        "question": "Describe the visible color of the inner globe illumination component?",
        "answer": "White"
      },
      {
        "question": "What is the type of mounting for this light fixture, as seen on the backplate?",
        "answer": "Wall"
      },
      {
        "question": "What design element is visible between each globe and the backplate?",
        "answer": "Arm"
      },
      {
        "question": "Is the backplate of the light fixture uniformly colored or patterned?",
        "answer": "Uniform"
      },
      {
        "question": "What is the apparent material of the backplate which supports the fixture?",
        "answer": "Metal"
      },
      {
        "question": "Considering the globes and backplate, what is the main style of the fixture?",
        "answer": "Modern"
      },
      {
        "question": "Besides the globes and backplate, what other visible parts are there?",
        "answer": "None"
      }
    ]
  }
]