[
  {
    "path": "images/small/6f/6fa7cbca.jpg"
  },
  {
    "questions": [
      {
        "question": "What is the predominant color of the chair's upholstery?",
        "answer": "Olive"
      },
      {
        "question": "What appears to be the primary material of the chair's seat and back?",
        "answer": "Fabric"
      },
      {
        "question": "Describe the overall shape of the chair's backrest?",
        "answer": "Curved"
      },
      {
        "question": "What kind of legs does the chair possess?",
        "answer": "Wooden"
      },
      {
        "question": "What is the visible texture of the chair's upholstery?",
        "answer": "Woven"
      },
      {
        "question": "Does the chair feature armrests? What is their style?",
        "answer": "Yes"
      },
      {
        "question": "What design element is visible on the chair's backrest?",
        "answer": "Tufted"
      },
      {
        "question": "Considering the legs, what is the chair's overall style?",
        "answer": "Traditional"
      },
      {
        "question": "What is the apparent finish of the chair's wooden legs?",
        "answer": "Natural"
      },
      {
        "question": "Based on the image, what is the chair's intended use?",
        "answer": "Dining"
      },
      {
        "question": "What is the color of the wooden legs in relation to the upholstery?",
        "answer": "Lighter"
      },
      {
        "question": "Describe the general visual form of the chair's silhouette?",
        "answer": "Tapered"
      },
      {
        "question": "How many legs does the chair visually appear to have?",
        "answer": "Four"
      },
      {
        "question": "Describe the overall visual impression of the chair\u2019s upholstery?",
        "answer": "Subdued"
      },
      {
        "question": "What is the style of the chair's armrest relative to the seat?",
        "answer": "Attached"
      }
    ]
  }
]