[
  {
    "path": "images/small/2d/2de57563.jpg"
  },
  {
    "questions": [
      {
        "question": "What is the predominant color of the necklace and pendant?",
        "answer": "Gold"
      },
      {
        "question": "What appears to be the primary material of the pendant?",
        "answer": "Metal"
      },
      {
        "question": "What is the overall shape of the pendant?",
        "answer": "Rectangular"
      },
      {
        "question": "What style of chain is used for this necklace?",
        "answer": "Cable"
      },
      {
        "question": "What is the main image depicted on the pendant's surface?",
        "answer": "Virgin"
      },
      {
        "question": "What kind of inscription surrounds the central image?",
        "answer": "Text"
      },
      {
        "question": "What is the apparent texture of the pendant's surface?",
        "answer": "Smooth"
      },
      {
        "question": "Describe the finish of the metal in the necklace and pendant.",
        "answer": "Shiny"
      },
      {
        "question": "What is the style of the border design on the pendant?",
        "answer": "Ornate"
      },
      {
        "question": "What is the apparent length of the pendant from top to bottom?",
        "answer": "Small"
      },
      {
        "question": "Describe the apparent thickness of the pendant.",
        "answer": "Thin"
      },
      {
        "question": "What is the apparent method of attachment of the pendant to the chain?",
        "answer": "Loop"
      },
      {
        "question": "What style of clasp is visible on the necklace?",
        "answer": "Spring"
      },
      {
        "question": "What is the overall style of the necklace, considering both pendant and chain?",
        "answer": "Religious"
      },
      {
        "question": "How many visible loops are there connecting the pendant to the chain?",
        "answer": "Two"
      }
    ]
  }
]