[
  {
    "path": "images/small/e2/e2e41809.jpg"
  },
  {
    "questions": [
      {
        "question": "What is the predominant color of the canvas upper on these casual shoes?",
        "answer": "Gray"
      },
      {
        "question": "What color is the accent panel visible on the side of each shoe?",
        "answer": "Red"
      },
      {
        "question": "Describe the color of the toe cap on these low-top sneakers?",
        "answer": "White"
      },
      {
        "question": "What material appears to constitute the majority of the visible shoe upper?",
        "answer": "Canvas"
      },
      {
        "question": "What type of closure system is employed on these lace-up shoes?",
        "answer": "Laces"
      },
      {
        "question": "Considering the overall style, what kind of shoes are these?",
        "answer": "Sneakers"
      },
      {
        "question": "What is the shape of the toe box on the displayed footwear?",
        "answer": "Round"
      },
      {
        "question": "What color are the laces used to secure these casual shoes?",
        "answer": "White"
      },
      {
        "question": "Based on the visible sole, what is the overall shoe profile?",
        "answer": "Low-top"
      },
      {
        "question": "Describe the apparent texture of the upper fabric on this footwear?",
        "answer": "Smooth"
      },
      {
        "question": "What is the general design style of these canvas shoes?",
        "answer": "Casual"
      },
      {
        "question": "Considering the sole's appearance, what is its likely material?",
        "answer": "Rubber"
      },
      {
        "question": "What is the construction of the sole, considering the image's clarity?",
        "answer": "Flat"
      },
      {
        "question": "Judging by the visible stitching, what is the primary construction method?",
        "answer": "Stitched"
      },
      {
        "question": "What is the overall visual impression of the footwear's design?",
        "answer": "Simple"
      }
    ]
  }
]