[
  {
    "path": "images/small/46/46dbb324.jpg"
  },
  {
    "questions": [
      {
        "question": "Considering the overall design, what is the predominant style of this leather shoe?",
        "answer": "Slip-on"
      },
      {
        "question": "Examining the material closely, what is the shoe primarily constructed from?",
        "answer": "Leather"
      },
      {
        "question": "Focusing on the color, what shade best describes the shoe's appearance?",
        "answer": "Tan"
      },
      {
        "question": "Based on the visible stitching and seams, what is the quality of the craftsmanship?",
        "answer": "Fine"
      },
      {
        "question": "Observing the sole, what material appears to be used for its construction?",
        "answer": "Rubber"
      },
      {
        "question": "Analyzing the shape of the toe, what style best fits its profile?",
        "answer": "Pointed"
      },
      {
        "question": "Considering the heel's height, would it be considered high or low?",
        "answer": "Low"
      },
      {
        "question": "What subtle design feature, visible along the top of the shoe, adds an element of visual interest?",
        "answer": "Seam"
      },
      {
        "question": "What is the apparent texture of the leather across the upper of the shoe?",
        "answer": "Smooth"
      },
      {
        "question": "Noticing the sole's interaction with the ground, is there any visible tread pattern?",
        "answer": "Plain"
      },
      {
        "question": "Considering the overall aesthetic, would this shoe be considered formal or informal?",
        "answer": "Formal"
      },
      {
        "question": "Focusing on the brand marking, can you identify a visible logo or branding element?",
        "answer": "Yes"
      },
      {
        "question": "Assessing the shoe's appearance, is the shine matte or glossy?",
        "answer": "Matte"
      },
      {
        "question": "What element on the inner side, usually near the heel, shows the size or some information?",
        "answer": "Label"
      },
      {
        "question": "Examining the shoe's construction, how many distinct pieces of leather appear visible?",
        "answer": "Two"
      }
    ]
  }
]