[
  {
    "path": "images/small/d5/d51c86c6.jpg"
  },
  {
    "questions": [
      {
        "question": "What is the dominant visible texture of the presented ottoman?",
        "answer": "Leather"
      },
      {
        "question": "What is the overall geometric shape of the displayed piece of furniture?",
        "answer": "Square"
      },
      {
        "question": "Considering the visible seams, what design element is prominently featured?",
        "answer": "Stitching"
      },
      {
        "question": "Describe the primary color shade observed across the ottoman's surface?",
        "answer": "Tan"
      },
      {
        "question": "What is the apparent material used for the main body of this furniture piece?",
        "answer": "Leather"
      },
      {
        "question": "Based on the visual, what is the general style of this home accent?",
        "answer": "Modern"
      },
      {
        "question": "Can you describe the visual appearance of the leather's finish?",
        "answer": "Smooth"
      },
      {
        "question": "What is the general shape of the visible edges of the ottoman's base?",
        "answer": "Squared"
      },
      {
        "question": "Considering its construction, what is the probable purpose of this object?",
        "answer": "Seating"
      },
      {
        "question": "Does the ottoman show any noticeable patterns or prints?",
        "answer": "No"
      },
      {
        "question": "What is the visible color tone of the ottoman's stitching?",
        "answer": "Tan"
      },
      {
        "question": "Describe the appearance of the visible seams; are they straight or curved?",
        "answer": "Straight"
      },
      {
        "question": "Is the piece of furniture shown designed with visible legs or feet?",
        "answer": "No"
      },
      {
        "question": "Describe the height of the piece relative to its width and depth.",
        "answer": "Low"
      },
      {
        "question": "Does the ottoman exhibit any signs of visible damage or wear?",
        "answer": "No"
      }
    ]
  }
]