[
  {
    "path": "images/small/01/0144bc0c.jpg"
  },
  {
    "questions": [
      {
        "question": "What is the predominant color scheme of the map displayed within the frame?",
        "answer": "Gray"
      },
      {
        "question": "What geographic area does the detailed map represent?",
        "answer": "SanFrancisco"
      },
      {
        "question": "What is the overall shape of the framed artwork presented?",
        "answer": "Rectangular"
      },
      {
        "question": "What appears to be the primary material of the frame itself?",
        "answer": "Black"
      },
      {
        "question": "What style of cartography is employed in the vintage map depiction?",
        "answer": "Grid"
      },
      {
        "question": "What is the apparent texture of the map's surface within the frame?",
        "answer": "Smooth"
      },
      {
        "question": "Considering the map's visual characteristics, what era does it appear to be from?",
        "answer": "Vintage"
      },
      {
        "question": "What appears to be the material of the artwork backing, behind the map?",
        "answer": "Paper"
      },
      {
        "question": "What type of border visually surrounds the central map illustration?",
        "answer": "Decorative"
      },
      {
        "question": "What text is prominently displayed at the top of the showcased map?",
        "answer": "Miniature"
      },
      {
        "question": "What seems to be the printing technique used for the map's details?",
        "answer": "Relief"
      },
      {
        "question": "Besides the map, are there any other noticeable elements within the frame?",
        "answer": "Text"
      },
      {
        "question": "What kind of lines are primarily used to delineate the streets or blocks?",
        "answer": "Straight"
      },
      {
        "question": "Does the frame show any signs of visible wear or weathering?",
        "answer": "No"
      },
      {
        "question": "What is the apparent overall aesthetic or style of the presented piece?",
        "answer": "Antique"
      }
    ]
  }
]