[
  {
    "path": "images/small/61/61241a70.jpg"
  },
  {
    "questions": [
      {
        "question": "What is the dominant color of the leather wallet displayed?",
        "answer": "Brown"
      },
      {
        "question": "What natural material appears to constitute the wallet's exterior?",
        "answer": "Leather"
      },
      {
        "question": "Considering the wallet's form, what is its primary design configuration?",
        "answer": "Bi-fold"
      },
      {
        "question": "What type of fastener is prominently visible on the left side of the wallet?",
        "answer": "Snap"
      },
      {
        "question": "What is the observable texture of the leather utilized in the wallet's construction?",
        "answer": "Grained"
      },
      {
        "question": "What securing mechanism is integrated into the smaller compartment of the wallet?",
        "answer": "Zipper"
      },
      {
        "question": "What is the overall shape of the product when closed, based solely on the visible image?",
        "answer": "Rectangular"
      },
      {
        "question": "What appears to be the brand's name embossed on the wallet?",
        "answer": "Eono"
      },
      {
        "question": "What is the apparent style of the visible stitching throughout the wallet?",
        "answer": "Topstitch"
      },
      {
        "question": "Describe the visible pattern of the wallet's leather surface texture",
        "answer": "Embossed"
      },
      {
        "question": "What type of pockets are clearly visible within the wallet's main compartment?",
        "answer": "Card"
      },
      {
        "question": "What color is the visible metal hardware present on the wallet?",
        "answer": "Gold"
      },
      {
        "question": "What is the visible method of closure for the primary section of the wallet?",
        "answer": "Snap"
      },
      {
        "question": "What is the overall visual impression of the wallet's condition?",
        "answer": "New"
      },
      {
        "question": "Based on the image, does the wallet appear to be made of a single piece of leather?",
        "answer": "No"
      }
    ]
  }
]