[
  {
    "path": "images/small/a0/a07b1539.jpg"
  },
  {
    "questions": [
      {
        "question": "What is the dominant color of the canvas upper material comprising the majority of the shoe's visible surface area?",
        "answer": "White"
      },
      {
        "question": "Considering the overall form, what is the fundamental shape of this footwear item, categorized broadly?",
        "answer": "Sneaker"
      },
      {
        "question": "Describe the textural quality of the main fabric section of the shoe, as visually apparent in the image?",
        "answer": "Smooth"
      },
      {
        "question": "What is the main material used in the construction of the upper portion of the shoe, ignoring accents or embellishments?",
        "answer": "Canvas"
      },
      {
        "question": "Observing the sole's structure, what is the visual style of its construction\u2014flat or elevated?",
        "answer": "Flat"
      },
      {
        "question": "How would you classify the closure mechanism of the shoe, considering its visible design features?",
        "answer": "Lace-up"
      },
      {
        "question": "Based on the visible components, what is the style of the shoe's toe area\u2014pointed, rounded, or otherwise?",
        "answer": "Rounded"
      },
      {
        "question": "What is the visual appearance of the laces in terms of their apparent material and color?",
        "answer": "White"
      },
      {
        "question": "Describe the apparent height of the shoe's sole relative to the upper, in terms of thickness or profile?",
        "answer": "Low"
      },
      {
        "question": "Judging from the image, what seems to be the overall design aesthetic of the shoe?",
        "answer": "Minimalist"
      },
      {
        "question": "Considering its construction, what is the most apparent feature of the shoe's heel design?",
        "answer": "Padded"
      },
      {
        "question": "What is the visible color of the eyelets through which the laces are threaded?",
        "answer": "Silver"
      },
      {
        "question": "What is the apparent texture of the shoe's sole from visual inspection?",
        "answer": "Smooth"
      },
      {
        "question": "What is the visible color of the inner lining of the shoe, peeking from the top edge?",
        "answer": "White"
      },
      {
        "question": "Describing the overall silhouette, what basic design category would you assign this shoe to?",
        "answer": "Casual"
      }
    ]
  }
]