[
  {
    "path": "images/small/97/97b97c47.jpg"
  },
  {
    "questions": [
      {
        "question": "What is the dominant color featured prominently on the phone case?",
        "answer": "Yellow"
      },
      {
        "question": "What letter is displayed inside the central heart shape?",
        "answer": "S"
      },
      {
        "question": "What geometric shape encloses the prominent letter on the phone case?",
        "answer": "Heart"
      },
      {
        "question": "What is the overall shape of the depicted product?",
        "answer": "Rectangular"
      },
      {
        "question": "What is the primary graphic design pattern shown on the case background?",
        "answer": "Stars"
      },
      {
        "question": "What secondary color accents the star pattern on the phone case?",
        "answer": "Pink"
      },
      {
        "question": "What is the apparent background color of the depicted phone case?",
        "answer": "Black"
      },
      {
        "question": "What appears to be the material of the phone case shown?",
        "answer": "Plastic"
      },
      {
        "question": "Describe the style of the lettering used for the prominent letter?",
        "answer": "Bold"
      },
      {
        "question": "What additional design elements besides stars are visible on the case?",
        "answer": "Swirls"
      },
      {
        "question": "What is the color of the letter within the heart on the case?",
        "answer": "Black"
      },
      {
        "question": "Considering the design, what is the likely intended use of this item?",
        "answer": "Protection"
      },
      {
        "question": "What is the texture implied by the image of the phone case shown?",
        "answer": "Smooth"
      },
      {
        "question": "What seems to be the print method used for the design on the case?",
        "answer": "Digital"
      },
      {
        "question": "Judging from the image, what is the overall visual aesthetic of the case?",
        "answer": "Girly"
      }
    ]
  }
]