[
  {
    "path": "images/small/dd/dd938fee.jpg"
  },
  {
    "questions": [
      {
        "question": "What is the predominant color of the chair's seat?",
        "answer": "Black"
      },
      {
        "question": "What material appears to constitute the chair's backrest?",
        "answer": "Mesh"
      },
      {
        "question": "What color is the mesh material of the chair's backrest?",
        "answer": "Gray"
      },
      {
        "question": "Describe the overall shape of the chair's armrests?",
        "answer": "Curved"
      },
      {
        "question": "What seems to be the material of the chair's armrests?",
        "answer": "Plastic"
      },
      {
        "question": "What is the apparent finish of the armrest's metallic components?",
        "answer": "Chrome"
      },
      {
        "question": "What is the texture of the chair's seat cushion?",
        "answer": "Smooth"
      },
      {
        "question": "What kind of design element is visible on the armrests' joints?",
        "answer": "Metallic"
      },
      {
        "question": "Judging by the image, what is the style of the chair?",
        "answer": "Office"
      },
      {
        "question": "Considering the materials, what is the chair's likely function?",
        "answer": "Sitting"
      },
      {
        "question": "What kind of support structure is visible beneath the armrests?",
        "answer": "Metallic"
      },
      {
        "question": "What is the overall appearance of the chair's back support?",
        "answer": "Ergonomic"
      },
      {
        "question": "What type of visual detailing is apparent on the armrests?",
        "answer": "Lines"
      },
      {
        "question": "Describe the visual connection between armrest and chair base?",
        "answer": "Integrated"
      },
      {
        "question": "Considering the visible parts, what is the chair's apparent state?",
        "answer": "New"
      }
    ]
  }
]