[
  {
    "path": "images/small/0e/0edfbae7.jpg"
  },
  {
    "questions": [
      {
        "question": "Considering the overall visual design, what is the predominant color scheme of the product packaging?",
        "answer": "Teal"
      },
      {
        "question": "Based on the typography and layout, what is the overall style of the product's branding?",
        "answer": "Minimalist"
      },
      {
        "question": "Observing the text, what is the primary advertised benefit of the product?",
        "answer": "Lifting"
      },
      {
        "question": "What is the implied shape of the product itself, based on how it is presented?",
        "answer": "Rectangular"
      },
      {
        "question": "Judging by the text's font and its size, what is the overall tone of the branding?",
        "answer": "Sophisticated"
      },
      {
        "question": "What language appears prominently, suggesting the product's primary market?",
        "answer": "English"
      },
      {
        "question": "What type of cosmetic product is explicitly named in the image's text?",
        "answer": "Sheet"
      },
      {
        "question": "From the branding, what is the product's most notable characteristic?",
        "answer": "Full"
      },
      {
        "question": "Considering the text's presentation, what is the intended application of this item?",
        "answer": "Facial"
      },
      {
        "question": "What is the name of the brand that manufactures this product?",
        "answer": "BELEI"
      },
      {
        "question": "In terms of visual cues, what is suggested about the product's texture?",
        "answer": "Smooth"
      },
      {
        "question": "What is the suggested material, considering the product packaging's visual appearance?",
        "answer": "Paper"
      },
      {
        "question": "What effect does the product description emphasize on the skin?",
        "answer": "Plumping"
      },
      {
        "question": "Judging by the visual elements and text, what kind of treatment does the product provide?",
        "answer": "Anti-ageing"
      },
      {
        "question": "From the overall presentation, what kind of audience is the product targeting?",
        "answer": "Adult"
      }
    ]
  }
]