[
  {
    "path": "images/small/2d/2d471111.jpg"
  },
  {
    "questions": [
      {
        "question": "What is the predominant color of the phone case's background design?",
        "answer": "Pink"
      },
      {
        "question": "What is the text prominently displayed on the phone case?",
        "answer": "Boss"
      },
      {
        "question": "What is the style of lettering used for the text on the phone case?",
        "answer": "Cursive"
      },
      {
        "question": "What word precedes 'Boss' in the text on the phone case?",
        "answer": "Girl"
      },
      {
        "question": "What color is the text 'Girl Boss' on the phone case?",
        "answer": "Black"
      },
      {
        "question": "Describe the visual texture of the phone case's background?",
        "answer": "Glittery"
      },
      {
        "question": "What shape is the phone case overall?",
        "answer": "Rectangular"
      },
      {
        "question": "What appears to be the material of the phone case?",
        "answer": "Plastic"
      },
      {
        "question": "What is the overall design style of the phone case?",
        "answer": "Girly"
      },
      {
        "question": "Is the glitter pattern on the case uniform or varied?",
        "answer": "Varied"
      },
      {
        "question": "Does the case appear to have any visible buttons or cutouts?",
        "answer": "Yes"
      },
      {
        "question": "What are the dominant colors in the glittery background?",
        "answer": "Pink"
      },
      {
        "question": "What kind of finish does the glitter give to the case?",
        "answer": "Shiny"
      },
      {
        "question": "What is the overall impression of the phone case’s design?",
        "answer": "Stylish"
      },
      {
        "question": "Considering the colors and design, who is the target audience for this phone case?",
        "answer": "Women"
      }
    ]
  }
]