[
  {
    "path": "images/small/81/81aaee3c.jpg"
  },
  {
    "questions": [
      {
        "question": "What is the dominant color of the visible wooden element?",
        "answer": "Gray"
      },
      {
        "question": "What appears to be the primary material used in construction?",
        "answer": "Wood"
      },
      {
        "question": "Describe the overall shape of the featured wooden component?",
        "answer": "Bulbous"
      },
      {
        "question": "What kind of finish is apparent on the wooden surface?",
        "answer": "Washed"
      },
      {
        "question": "Considering the grain, what texture is suggested by the wood?",
        "answer": "Smooth"
      },
      {
        "question": "What is the apparent color of the decorative bottom band?",
        "answer": "Gold"
      },
      {
        "question": "How many distinct sections or parts make up this object?",
        "answer": "Three"
      },
      {
        "question": "What design style best encapsulates this object's aesthetic?",
        "answer": "Classic"
      },
      {
        "question": "Does the wood exhibit a noticeable linear grain pattern?",
        "answer": "Yes"
      },
      {
        "question": "Is the object's surface uniformly colored, or does it show variation?",
        "answer": "Varied"
      },
      {
        "question": "What kind of visual effect does the color variation create?",
        "answer": "Distressed"
      },
      {
        "question": "What is the shape of the topmost portion of the item?",
        "answer": "Baluster"
      },
      {
        "question": "What is the apparent craftsmanship of the piece's components?",
        "answer": "Turned"
      },
      {
        "question": "Does the wood show signs of significant knots or imperfections?",
        "answer": "No"
      },
      {
        "question": "What is the approximate visual height-to-width ratio?",
        "answer": "Tall"
      }
    ]
  }
]