[
  {
    "path": "images/small/bf/bff7bcb6.jpg"
  },
  {
    "questions": [
      {
        "question": "What is the predominant color of the power adapter's casing?",
        "answer": "Black"
      },
      {
        "question": "What type of plug does the power adapter utilize?",
        "answer": "US"
      },
      {
        "question": "What material appears to be used for the power adapter's outer shell?",
        "answer": "Plastic"
      },
      {
        "question": "What is the overall shape of the main power adapter body?",
        "answer": "Rectangular"
      },
      {
        "question": "Considering the cable, what is the adapter's apparent functionality?",
        "answer": "Power"
      },
      {
        "question": "Describe the texture of the visible surface of the adapter.",
        "answer": "Smooth"
      },
      {
        "question": "What is the apparent length of the power cord shown?",
        "answer": "Short"
      },
      {
        "question": "Is there any visible branding or markings on the adapter?",
        "answer": "Yes"
      },
      {
        "question": "What type of cable is attached to the power adapter?",
        "answer": "Electrical"
      },
      {
        "question": "How many prongs are present in the AC power plug?",
        "answer": "Two"
      },
      {
        "question": "Based on the image, are there any visible screws on the casing?",
        "answer": "No"
      },
      {
        "question": "What is the apparent finish of the external plastic casing?",
        "answer": "Matte"
      },
      {
        "question": "Does the image show any visible damage or defects on the product?",
        "answer": "No"
      },
      {
        "question": "Describe the general orientation of the power plug itself.",
        "answer": "Horizontal"
      },
      {
        "question": "What is the general condition of the power cable visible?",
        "answer": "Intact"
      }
    ]
  }
]