[
  {
    "path": "images/small/22/228940ef.jpg"
  },
  {
    "questions": [
      {
        "question": "What is the dominant pattern visibly present across all the linens?",
        "answer": "Gingham"
      },
      {
        "question": "What is the primary color of the larger visible squares in the gingham pattern?",
        "answer": "Navy"
      },
      {
        "question": "What is the primary color of the smaller visible squares in the gingham pattern?",
        "answer": "White"
      },
      {
        "question": "Considering the fabric's visual texture, what is its apparent weave type?",
        "answer": "Woven"
      },
      {
        "question": "What is the apparent material type of the displayed bedding set, based on its visual appearance?",
        "answer": "Cotton"
      },
      {
        "question": "Observing the overall arrangement, what type of bedding is depicted in the image?",
        "answer": "Sheets"
      },
      {
        "question": "How many pillowcases are prominently displayed and folded within the image?",
        "answer": "Two"
      },
      {
        "question": "Based on visual folds, what is the general shape of the main sheet component?",
        "answer": "Rectangular"
      },
      {
        "question": "Considering the image, what is the visual state of the bedding items; are they used or unused?",
        "answer": "Unused"
      },
      {
        "question": "What is the apparent weight or thickness of the displayed fabric; is it light or heavy?",
        "answer": "Light"
      },
      {
        "question": "Based on the image, what is the level of sheen or glossiness of the fabric?",
        "answer": "Matte"
      },
      {
        "question": "What is the color variation within the gingham squares; is it uniform or variegated?",
        "answer": "Uniform"
      },
      {
        "question": "Is there any visible embroidery, lace, or other decorative elements on the sheets?",
        "answer": "No"
      },
      {
        "question": "Judging by the image, what is the overall visual style of the bedding set; is it modern or traditional?",
        "answer": "Traditional"
      },
      {
        "question": "Disregarding the pattern, what is the general color family of the bedding set?",
        "answer": "Blue"
      }
    ]
  }
]